pytroll_watchers/__init__.py
pytroll_watchers/common.py
pytroll_watchers/dataspace_watcher.py
pytroll_watchers/datastore_watcher.py
pytroll_watchers/dhus_watcher.py
pytroll_watchers/fetch.py
pytroll_watchers/local_watcher.py
pytroll_watchers/main_interface.py
pytroll_watchers/minio_notification_watcher.py
pytroll_watchers/publisher.py
pytroll_watchers/selector.py
pytroll_watchers/testing.py
pytroll_watchers/version.py
pytroll_watchers/backends/__init__.py
pytroll_watchers/backends/local.py
pytroll_watchers-0.5.0.dist-info/METADATA
pytroll_watchers-0.5.0.dist-info/WHEEL
pytroll_watchers-0.5.0.dist-info/entry_points.txt
pytroll_watchers-0.5.0.dist-info/licenses/LICENSE.txt
pytroll_watchers-0.5.0.dist-info/RECORD
