Metadata-Version: 2.4
Name: pytroll-watchers
Version: 0.5.0
Summary: Utility functions and scripts to watch for new files on local or remote filesystems.
Project-URL: Documentation, https://pytroll-watchers.readthedocs.io/en/latest/
Author-email: Martin Raspaud <martin.raspaud@smhi.se>
License:                     GNU GENERAL PUBLIC LICENSE
License-File: LICENSE.txt
Classifier: Development Status :: 4 - Beta
Classifier: Intended Audience :: Developers
Classifier: License :: OSI Approved :: GNU General Public License v3 or later (GPLv3+)
Classifier: Operating System :: OS Independent
Classifier: Programming Language :: Python
Classifier: Topic :: Communications
Requires-Python: >=3.10
Requires-Dist: geojson
Requires-Dist: pyyaml
Requires-Dist: trollsift
Requires-Dist: universal-pathlib>=0.2.5
Provides-Extra: dataspace
Requires-Dist: oauthlib; extra == 'dataspace'
Requires-Dist: requests-oauthlib; extra == 'dataspace'
Requires-Dist: s3fs; extra == 'dataspace'
Provides-Extra: datastore
Requires-Dist: aiohttp; extra == 'datastore'
Requires-Dist: oauthlib; extra == 'datastore'
Requires-Dist: requests-oauthlib; extra == 'datastore'
Provides-Extra: dhus
Requires-Dist: aiohttp; extra == 'dhus'
Requires-Dist: defusedxml; extra == 'dhus'
Requires-Dist: requests; extra == 'dhus'
Provides-Extra: local
Requires-Dist: watchdog; extra == 'local'
Provides-Extra: minio
Requires-Dist: minio; extra == 'minio'
Requires-Dist: s3fs; extra == 'minio'
Provides-Extra: publishing
Requires-Dist: posttroll; extra == 'publishing'
Provides-Extra: selector
Requires-Dist: redis; extra == 'selector'
Provides-Extra: ssh
Requires-Dist: paramiko; extra == 'ssh'
Provides-Extra: tests
Requires-Dist: aiohttp; extra == 'tests'
Requires-Dist: defusedxml; extra == 'tests'
Requires-Dist: freezegun; extra == 'tests'
Requires-Dist: minio; extra == 'tests'
Requires-Dist: oauthlib; extra == 'tests'
Requires-Dist: paramiko; extra == 'tests'
Requires-Dist: posttroll; extra == 'tests'
Requires-Dist: redis; extra == 'tests'
Requires-Dist: redis-server; extra == 'tests'
Requires-Dist: requests; extra == 'tests'
Requires-Dist: requests-oauthlib; extra == 'tests'
Requires-Dist: responses; extra == 'tests'
Requires-Dist: s3fs; extra == 'tests'
Requires-Dist: watchdog; extra == 'tests'
